INSTALL.rst
LICENSE
MANIFEST.in
README.rst
VERSION
requirements.txt
setup.py
tasks.py
src/django_model_reference.egg-info/PKG-INFO
src/django_model_reference.egg-info/SOURCES.txt
src/django_model_reference.egg-info/dependency_links.txt
src/django_model_reference.egg-info/not-zip-safe
src/django_model_reference.egg-info/requires.txt
src/django_model_reference.egg-info/top_level.txt
src/model_reference/__init__.py
src/model_reference/__main__.py
src/model_reference/__meta__.py
src/model_reference/apps.py
src/model_reference/models.py
src/model_reference/utils.py
src/model_reference/migrations/__init__.py
src/model_reference/tests/__init__.py
src/model_reference/tests/__main__.py
src/model_reference/tests/test_documentation.py
src/model_reference/tests/test_model_reference.py